{
  "abilitys": [
    {
      "id": 1,
      "abilityname": "공격력 증가?",
      "abilityinfo": "잠재능력 설명 1",
      "type": 1,
      "value": 10
    },
    {
      "id": 2,
      "abilityname": "뭔가 증가?",
      "abilityinfo": "잠재능력 설명 2",
      "type": 2,
      "value": 10
    },
    {
      "id": 3,
      "abilityname": "ㅇㅇㅇㅇ",
      "abilityinfo": "잠재능력 설명 3",
      "type": 3,
      "value": 10
    },
    {
      "id": 4,
      "abilityname": "ㅁㅁㅁㅁ",
      "abilityinfo": "잠재능력 설명 4",
      "type": 4,
      "value": 10
    }
  ]
}